MANIFEST.in
README.md
setup.cfg
setup.py
Cybot/__init__.py
Cybot/glance.py
Cybot/helper.py
Cybot.egg-info/PKG-INFO
Cybot.egg-info/SOURCES.txt
Cybot.egg-info/dependency_links.txt
Cybot.egg-info/requires.txt
Cybot.egg-info/top_level.txt
Cybot/webwhatsapi/__init__.py
Cybot/webwhatsapi/async_driver.py
Cybot/webwhatsapi/consts.py
Cybot/webwhatsapi/helper.py
Cybot/webwhatsapi/wapi_js_wrapper.py
Cybot/webwhatsapi/objects/__init__.py
Cybot/webwhatsapi/objects/chat.py
Cybot/webwhatsapi/objects/contact.py
Cybot/webwhatsapi/objects/message.py
Cybot/webwhatsapi/objects/number_status.py
Cybot/webwhatsapi/objects/whatsapp_object.py
cybot/Cybot/instagram/ImageUtils.py
cybot/Cybot/instagram/InstagramAPI.py
cybot/Cybot/instagram/__init__.py
cybot/Cybot/instagram/exceptions.py
cybot/Cybot/messenger/__init__.py
cybot/Cybot/telegram/__init__.py
cybot/Cybot/telegram/config.py
cybot/Cybot/telegram/inline.py
cybot/Cybot/telegram/loop.py
cybot/Cybot/telegram/metodos.py
cybot/Cybot/telegram/flask/__init__.py
cybot/Cybot/telegram/flask/__main__.py
cybot/Cybot/telegram/flask/_compat.py
cybot/Cybot/telegram/flask/app.py
cybot/Cybot/telegram/flask/blueprints.py
cybot/Cybot/telegram/flask/cli.py
cybot/Cybot/telegram/flask/config.py
cybot/Cybot/telegram/flask/ctx.py
cybot/Cybot/telegram/flask/debughelpers.py
cybot/Cybot/telegram/flask/globals.py
cybot/Cybot/telegram/flask/helpers.py
cybot/Cybot/telegram/flask/logging.py
cybot/Cybot/telegram/flask/sessions.py
cybot/Cybot/telegram/flask/signals.py
cybot/Cybot/telegram/flask/templating.py
cybot/Cybot/telegram/flask/testing.py
cybot/Cybot/telegram/flask/utils.py
cybot/Cybot/telegram/flask/views.py
cybot/Cybot/telegram/flask/wrappers.py
cybot/Cybot/telegram/flask/json/__init__.py
cybot/Cybot/telegram/flask/json/tag.py
cybot/Cybot/whatsapp/__init__.py
cybot/Cybot/whatsapp/dual.py
cybot/Cybot/whatsapp/glance.py
cybot/Cybot/whatsapp/return.py
cybot/Cybot/whatsapp/untitled.py
cybot/Cybot/whatsapp/webwhatsapi/objects/__init__.py
cybot/Cybot/whatsapp/webwhatsapi/objects/chat.py
cybot/Cybot/whatsapp/webwhatsapi/objects/contact.py
cybot/Cybot/whatsapp/webwhatsapi/objects/message.py
