Metadata-Version: 1.2
Name: Cybot
Version: 0.0.12
Summary: Whatsapp framework bot
Home-page: https://github.com/Francis-Taylor/Cybot
Author: Francis Taylor
Author-email: FrancisTrapp2000@gmail.com
License: MIT
Download-URL: https://github.com/francis-taylor/Cybot.git
Keywords: whatsapp,Bot,Python,whatsapp-bot,framework
Platform: UNKNOWN
Classifier: Development Status :: 3 - Alpha
Classifier: Intended Audience :: Developers
Classifier: Topic :: Software Development :: Build Tools
Classifier: License :: OSI Approved :: MIT License
Classifier: Programming Language :: Python :: 3
Classifier: Programming Language :: Python :: 3.4
Classifier: Programming Language :: Python :: 3.5
Classifier: Programming Language :: Python :: 3.6
Requires-Python: >=3.6
